bok_drone_onboard_system/__init__.py
bok_drone_onboard_system/bno08x_acquire.py
bok_drone_onboard_system/survey_acquire.py
bok_drone_onboard_system/bno/__init__.py
bok_drone_onboard_system/positioner/__init__.py
bok_drone_onboard_system/survey/__init__.py
bok_drone_onboard_system/survey/emlid_reader.py
bok_drone_onboard_system-0.1.12.dist-info/licenses/LICENSE
bok_drone_onboard_system-0.1.12.dist-info/METADATA
bok_drone_onboard_system-0.1.12.dist-info/WHEEL
bok_drone_onboard_system-0.1.12.dist-info/entry_points.txt
bok_drone_onboard_system-0.1.12.dist-info/top_level.txt
bok_drone_onboard_system-0.1.12.dist-info/RECORD
